<?xml version="1.0" encoding="UTF-8" standalone="no"?>
<configuration>
<topRightX>630.0</topRightX>
<topRightY>22.0</topRightY>
<topLeftX>16.0</topLeftX>
<topLeftY>13.0</topLeftY>
<bottomRightX>614.0</bottomRightX>
<bottomRightY>474.0</bottomRightY>
<bottomLeftX>6.0</bottomLeftX>
<bottomLeftY>470.0</bottomLeftY>
<ballYUpper>127</ballYUpper>
<ballYLower>127</ballYLower>
<ballUUpper>127</ballUUpper>
<ballULower>127</ballULower>
<ballVUpper>127</ballVUpper>
<ballVLower>127</ballVLower>
<teamYUpper>184</teamYUpper>
<teamYLower>112</teamYLower>
<teamUUpper>188</teamUUpper>
<teamULower>136</teamULower>
<teamVUpper>127</teamVUpper>
<teamVLower>100</teamVLower>
<greenYUpper>255</greenYUpper>
<greenYLower>228</greenYLower>
<greenUUpper>139</greenUUpper>
<greenULower>106</greenULower>
<greenVUpper>127</greenVUpper>
<greenVLower>108</greenVLower>
<groundYUpper>127</groundYUpper>
<groundYLower>127</groundYLower>
<groundUUpper>127</groundUUpper>
<groundULower>127</groundULower>
<groundVUpper>127</groundVUpper>
<groundVLower>127</groundVLower>
<opponentYUpper>127</opponentYUpper>
<opponentYLower>127</opponentYLower>
<opponentUUpper>127</opponentUUpper>
<opponentULower>127</opponentULower>
<opponentVUpper>127</opponentVUpper>
<opponentVLower>127</opponentVLower>
</configuration>
